pybind11_jsoncons/__init__.pyi
pybind11_jsoncons/__main__.py
pybind11_jsoncons/_core.cpython-313-x86_64-linux-gnu.so
pybind11_jsoncons/__init__.py
pybind11_jsoncons-0.1.2.dist-info/METADATA
pybind11_jsoncons-0.1.2.dist-info/RECORD
pybind11_jsoncons-0.1.2.dist-info/WHEEL
pybind11_jsoncons-0.1.2.dist-info/licenses/LICENSE
